nextpy/__init__.py
nextpy/cli.py
nextpy/config.py
nextpy/project_generator.py
nextpy/prompts.py
nextpy/templates/docker/.gitkeep
nextpy/templates/docker/Dockerfile.backend
nextpy/templates/docker/Dockerfile.next
nextpy/templates/docker/Dockerfile.vite
nextpy/templates/docker/docker-compose-mongo.yml
nextpy/templates/docker/docker-compose-postgres.yml
nextpy/templates/docker/docker-compose-sqlite.yml
nextpy/templates/fastapi/.env-mongo
nextpy/templates/fastapi/.env-postgres
nextpy/templates/fastapi/.env-sqlite
nextpy/templates/fastapi/.gitkeep
nextpy/templates/fastapi/gitignore.template
nextpy/templates/fastapi/main-mongo.py
nextpy/templates/fastapi/main-postgres.py
nextpy/templates/fastapi/main-sqlite.py
nextpy/templates/fastapi/main.py
nextpy/templates/fastapi/requirements-mongo.txt
nextpy/templates/fastapi/requirements-postgres.txt
nextpy/templates/fastapi/requirements-sqlite.txt
nextpy/templates/git/.gitkeep
nextpy/templates/git/gitignore.template
nextpy/templates/next/.gitkeep
nextpy/templates/next/env.local.template
nextpy/templates/next/gitignore.template
nextpy/templates/vite/.gitkeep
nextpy_cli-1.1.1.dist-info/METADATA
nextpy_cli-1.1.1.dist-info/WHEEL
nextpy_cli-1.1.1.dist-info/entry_points.txt
nextpy_cli-1.1.1.dist-info/top_level.txt
nextpy_cli-1.1.1.dist-info/RECORD
